pyissm/__init__.py
pyissm/plot.py
pyissm/analysis/__init__.py
pyissm/analysis/ismip.py
pyissm/data/__init__.py
pyissm/data/interp.py
pyissm/learn/__init__.py
pyissm/learn/tutorials.py
pyissm/model/Model.py
pyissm/model/__init__.py
pyissm/model/bc.py
pyissm/model/execute.py
pyissm/model/io.py
pyissm/model/mesh.py
pyissm/model/param.py
pyissm/model/classes/__init__.py
pyissm/model/classes/amr.py
pyissm/model/classes/autodiff.py
pyissm/model/classes/balancethickness.py
pyissm/model/classes/basalforcings.py
pyissm/model/classes/calving.py
pyissm/model/classes/class_registry.py
pyissm/model/classes/class_utils.py
pyissm/model/classes/cluster.py
pyissm/model/classes/constants.py
pyissm/model/classes/damage.py
pyissm/model/classes/debris.py
pyissm/model/classes/debug.py
pyissm/model/classes/dependent.py
pyissm/model/classes/dsl.py
pyissm/model/classes/esa.py
pyissm/model/classes/flowequation.py
pyissm/model/classes/friction.py
pyissm/model/classes/frontalforcings.py
pyissm/model/classes/geometry.py
pyissm/model/classes/groundingline.py
pyissm/model/classes/hydrology.py
pyissm/model/classes/independent.py
pyissm/model/classes/initialization.py
pyissm/model/classes/inversion.py
pyissm/model/classes/issmsettings.py
pyissm/model/classes/levelset.py
pyissm/model/classes/love.py
pyissm/model/classes/lovenumbers.py
pyissm/model/classes/mask.py
pyissm/model/classes/massfluxatgate.py
pyissm/model/classes/masstransport.py
pyissm/model/classes/materials.py
pyissm/model/classes/mesh.py
pyissm/model/classes/miscellaneous.py
pyissm/model/classes/misfit.py
pyissm/model/classes/nodalvalue.py
pyissm/model/classes/offlinesolidearthsolution.py
pyissm/model/classes/organizer.py
pyissm/model/classes/outputdefinition.py
pyissm/model/classes/private.py
pyissm/model/classes/qmu.py
pyissm/model/classes/radaroverlay.py
pyissm/model/classes/regionaloutput.py
pyissm/model/classes/results.py
pyissm/model/classes/rifts.py
pyissm/model/classes/rotational.py
pyissm/model/classes/sampling.py
pyissm-0.0.1.dev190126.dist-info/licenses/LICENSE
pyissm-0.0.1.dev190126.dist-info/METADATA
pyissm-0.0.1.dev190126.dist-info/WHEEL
pyissm-0.0.1.dev190126.dist-info/top_level.txt
pyissm-0.0.1.dev190126.dist-info/RECORD
