Metadata-Version: 2.4
Name: pyissm
Version: 0.0.1.dev190126
Summary: Python API for the Ice-sheet and Sea-level System Model (ISSM), managed by ACCESS-NRI
Author: ACCESS-NRI
License: Apache-2.0
Project-URL: Homepage, https://github.com/ACCESS-NRI/pyISSM
Project-URL: Repository, https://github.com/ACCESS-NRI/pyISSM
Project-URL: Issues, https://github.com/ACCESS-NRI/pyISSM/issues
Classifier: Development Status :: 2 - Pre-Alpha
Classifier: Programming Language :: Python :: 3
Classifier: License :: OSI Approved :: Apache Software License
Classifier: Operating System :: OS Independent
Requires-Python: >=3.9
License-File: LICENSE
Requires-Dist: xarray
Requires-Dist: numpy
Requires-Dist: scipy
Requires-Dist: netCDF4
Requires-Dist: pandas
Requires-Dist: matplotlib
Requires-Dist: attrs
Requires-Dist: PyYAML
Dynamic: license-file
